gpu_waiter/__init__.py
gpu_waiter/main.py
gpu_waiter/tasker.py
gpu_waiter/utils.py
gpu_waiter/waiter.py
gpu_waiter/device/__init__.py
gpu_waiter/device/device.py
gpu_waiter/device/nvgpu.py
gpu_waiter-0.1.5.dist-info/LICENSE
gpu_waiter-0.1.5.dist-info/METADATA
gpu_waiter-0.1.5.dist-info/WHEEL
gpu_waiter-0.1.5.dist-info/entry_points.txt
gpu_waiter-0.1.5.dist-info/top_level.txt
gpu_waiter-0.1.5.dist-info/RECORD
