Metadata-Version: 2.1
Name: gpu_waiter
Version: 0.1.5
Summary: a gpu device moniter could automaticly run command if device available, just for nvidia gpu.
Author-email: lijunjie2232 <2533584225@qq.com>
Maintainer-email: lijunjie2232 <2533584225@qq.com>
Project-URL: Homepage, https://pypi.org/project/gpu-waiter
Project-URL: Repository, https://github.com/lijunjie2232/gpu_waiter.git
Project-URL: Issues, https://github.com/lijunjie2232/gpu_waiter/issues
License-File: LICENSE
Requires-Dist: nvitop
